condo/__init__.py
condo/adapter_gaussian_ot.py
condo/adapter_mmd.py
condo/adapter_wd.py
condo/condo_adapter_kld.py
condo/condo_adapter_mmd.py
condo/condo_adapter_wd.py
condo/kernels.py
condo/ot.py
condo/product_prior.py
condo/utils.py
condo-1.0.0.dist-info/LICENSE
condo-1.0.0.dist-info/METADATA
condo-1.0.0.dist-info/WHEEL
condo-1.0.0.dist-info/top_level.txt
condo-1.0.0.dist-info/zip-safe
condo-1.0.0.dist-info/RECORD
