Metadata-Version: 2.1
Name: condo
Version: 1.0.0
Summary: Confounded domain adaptation
Home-page: http://github.com/calvinmccarter/condo-adapter
Author: Calvin McCarter
Author-email: Calvin McCarter <mccarter.calvin@gmail.com>
Maintainer: Calvin McCarter
Maintainer-email: Calvin McCarter <mccarter.calvin@gmail.com>
Project-URL: Homepage, http://github.com/calvinmccarter/condo-adapter
Keywords: domain adaptation,tabular,confounding,batch correction
Classifier: Development Status :: 3 - Alpha
Classifier: Intended Audience :: Developers
Classifier: Intended Audience :: Science/Research
Classifier: License :: OSI Approved
Classifier: Operating System :: MacOS
Classifier: Operating System :: Microsoft :: Windows
Classifier: Operating System :: POSIX
Classifier: Operating System :: Unix
Classifier: Programming Language :: Python
Classifier: Programming Language :: Python :: 3.6
Classifier: Programming Language :: Python :: 3.7
Classifier: Programming Language :: Python :: 3.8
Classifier: Programming Language :: Python :: 3.9
Classifier: Topic :: Scientific/Engineering
Classifier: Topic :: Software Development
License-File: LICENSE
Requires-Dist: miceforest <6.0.0
Requires-Dist: numpy
Requires-Dist: pandas
Requires-Dist: pytorch-minimize >=0.0.2
Requires-Dist: scipy
Requires-Dist: scikit-learn
Requires-Dist: torch >=1.4.0
Requires-Dist: tqdm
